rinject/__init__.py
rInject-0.1.2.dist-info/LICENSE
rInject-0.1.2.dist-info/METADATA
rInject-0.1.2.dist-info/WHEEL
rInject-0.1.2.dist-info/top_level.txt
rInject-0.1.2.dist-info/RECORD
