Metadata-Version: 2.1
Name: rInject
Version: 0.1.2
Summary: A flexible (annotations or keys) but simple dependency injection library for Python 3.
Home-page: https://github.com/stevemccartney/rinject
Author: Steve McCartney
Author-email: python@reconvergent.com
License: Apache 2.0
Keywords: dependency injection inject injector di dic
Classifier: Development Status :: 4 - Beta
Classifier: Intended Audience :: Developers
Classifier: Programming Language :: Python :: 3.8
Requires-Python: >=3.8
License-File: LICENSE
Provides-Extra: dev
Requires-Dist: pytest ; extra == 'dev'
